postcodes.py
setup.py
Postcodes.egg-info/PKG-INFO
Postcodes.egg-info/SOURCES.txt
Postcodes.egg-info/dependency_links.txt
Postcodes.egg-info/not-zip-safe
Postcodes.egg-info/top_level.txt