Metadata-Version: 1.1
Name: Postcodes
Version: 0.1
Summary: A simple library for getting access to UK Postcode data,including latitide and longitude and administrative information. You can also search for other postcodes withina distance of a point or other postcode.
Home-page: http://github.com/e-dard/postcodes
Author: Edward Robinson
Author-email: me@eddrobinson.net
License: WTFPL
Platform: any
Classifier: Environment :: Web Environment
Classifier: Intended Audience :: Developers
Classifier: License :: Other/Proprietary License
Classifier: Operating System :: OS Independent
Classifier: Programming Language :: Python
Classifier: Topic :: Internet :: WWW/HTTP :: Dynamic Content
Classifier: Topic :: Software Development :: Libraries :: Python Modules
